cross3d/__init__.py
cross3d/constants.py
cross3d/enum.py
cross3d/abstract/__init__.py
cross3d/abstract/abstractapplication.py
cross3d/abstract/abstractcontainer.py
cross3d/abstract/abstractexceptionrouter.py
cross3d/abstract/abstractgroup.py
cross3d/abstract/abstractscene.py
cross3d/abstract/abstractsceneanimationcontroller.py
cross3d/abstract/abstractsceneanimationkey.py
cross3d/abstract/abstractsceneatmospheric.py
cross3d/abstract/abstractscenecache.py
cross3d/abstract/abstractscenecamera.py
cross3d/abstract/abstractscenefx.py
cross3d/abstract/abstractscenelayer.py
cross3d/abstract/abstractscenelayergroup.py
cross3d/abstract/abstractscenemap.py
cross3d/abstract/abstractscenematerial.py
cross3d/abstract/abstractscenemodel.py
cross3d/abstract/abstractsceneobject.py
cross3d/abstract/abstractscenepropset.py
cross3d/abstract/abstractscenerenderer.py
cross3d/abstract/abstractscenerenderpass.py
cross3d/abstract/abstractsceneviewport.py
cross3d/abstract/abstractscenewrapper.py
cross3d/abstract/abstractundocontext.py
cross3d/abstract/abstractuserprops.py
cross3d/abstract/collection.py
cross3d/abstract/external.py
cross3d/classes/__init__.py
cross3d/classes/clipboard.py
cross3d/classes/dispatch.py
cross3d/classes/dispatchprocess.py
cross3d/classes/exceptions.py
cross3d/classes/fcurve.py
cross3d/classes/filesequence.py
cross3d/classes/flipbook.py
cross3d/classes/framerange.py
cross3d/classes/signalinspector.py
cross3d/classes/timecode.py
cross3d/classes/valuerange.py
cross3d/maya/__init__.py
cross3d/maya/collection.py
cross3d/maya/external.py
cross3d/maya/mayaapplication.py
cross3d/maya/mayaexceptionrouter.py
cross3d/maya/mayagroup.py
cross3d/maya/mayascene.py
cross3d/maya/mayascenecamera.py
cross3d/maya/mayascenematerial.py
cross3d/maya/mayascenemodel.py
cross3d/maya/mayasceneobject.py
cross3d/maya/mayasceneviewport.py
cross3d/maya/mayascenewrapper.py
cross3d/maya/mayauserprops.py
cross3d/migrate/__init__.py
cross3d-0.1.0.dist-info/DESCRIPTION.rst
cross3d-0.1.0.dist-info/METADATA
cross3d-0.1.0.dist-info/RECORD
cross3d-0.1.0.dist-info/WHEEL
cross3d-0.1.0.dist-info/metadata.json
cross3d-0.1.0.dist-info/top_level.txt
