Metadata-Version: 2.0
Name: cross3d
Version: 0.1.0
Summary: A unified API allowing to interact with multiple 3D content creation packages.
Home-page: https://github.com/blurstudio/cross3d
Author: Blur Studio
Author-email: github@blurstudio.com
License: GPL
Keywords: 3d autodesk dcc vfx python qt 3dmax softimage xsi maya motionbuilder
Platform: UNKNOWN
Classifier: Development Status :: 4 - Beta
Classifier: Intended Audience :: Developers
Classifier: Topic :: Artistic Software
Classifier: License :: OSI Approved :: GNU General Public License (GPL)
Classifier: Programming Language :: Python :: 2.7
